RenderMolecules/ElementData.py
RenderMolecules/RenderMolecules.py
RenderMolecules/__init__.py
RenderMolecules/blenderUtils.py
RenderMolecules/geometryUtils.py
RenderMolecules/otherUtils.py
rendermolecules-0.0.1.dist-info/licenses/LICENSE
rendermolecules-0.0.1.dist-info/METADATA
rendermolecules-0.0.1.dist-info/WHEEL
rendermolecules-0.0.1.dist-info/top_level.txt
rendermolecules-0.0.1.dist-info/RECORD
