Metadata-Version: 2.4
Name: RenderMolecules
Version: 0.0.1
Summary: A way to render molecules in Blender
Author-email: Tobias Dijkhuis <t.m.dijkhuis@lic.leidenuniv.nl>
Keywords: molecules,chemistry,blender,rendering,quantum
Requires-Python: <3.12,>=3.8
License-File: LICENSE
Requires-Dist: bpy
Requires-Dist: numpy
Dynamic: license-file
